LICENSE
MANIFEST.in
README.md
pyproject.toml
setup.cfg
setup.py
data_pipelines_cli/__init__.py
data_pipelines_cli/__main__.py
data_pipelines_cli/airbyte_utils.py
data_pipelines_cli/bi_utils.py
data_pipelines_cli/cli.py
data_pipelines_cli/cli_configs.py
data_pipelines_cli/cli_constants.py
data_pipelines_cli/cli_utils.py
data_pipelines_cli/config_generation.py
data_pipelines_cli/data_structures.py
data_pipelines_cli/dbt_utils.py
data_pipelines_cli/docker_response_reader.py
data_pipelines_cli/errors.py
data_pipelines_cli/filesystem_utils.py
data_pipelines_cli/io_utils.py
data_pipelines_cli/jinja.py
data_pipelines_cli/looker_utils.py
data_pipelines_cli/vcs_utils.py
data_pipelines_cli.egg-info/PKG-INFO
data_pipelines_cli.egg-info/SOURCES.txt
data_pipelines_cli.egg-info/dependency_links.txt
data_pipelines_cli.egg-info/entry_points.txt
data_pipelines_cli.egg-info/requires.txt
data_pipelines_cli.egg-info/top_level.txt
data_pipelines_cli/cli_commands/__init__.py
data_pipelines_cli/cli_commands/clean.py
data_pipelines_cli/cli_commands/compile.py
data_pipelines_cli/cli_commands/create.py
data_pipelines_cli/cli_commands/deploy.py
data_pipelines_cli/cli_commands/docs.py
data_pipelines_cli/cli_commands/init.py
data_pipelines_cli/cli_commands/prepare_env.py
data_pipelines_cli/cli_commands/publish.py
data_pipelines_cli/cli_commands/run.py
data_pipelines_cli/cli_commands/seed.py
data_pipelines_cli/cli_commands/template.py
data_pipelines_cli/cli_commands/test.py
data_pipelines_cli/cli_commands/update.py
data_pipelines_cli/cli_commands/generate/__init__.py
data_pipelines_cli/cli_commands/generate/databricks_job.py
data_pipelines_cli/cli_commands/generate/generate.py
data_pipelines_cli/cli_commands/generate/model_yaml.py
data_pipelines_cli/cli_commands/generate/source_sql.py
data_pipelines_cli/cli_commands/generate/source_yaml.py
data_pipelines_cli/cli_commands/generate/utils.py
tests/test_airbyte_utils.py
tests/test_bi_utils.py
tests/test_cli_utils.py
tests/test_config_generation.py
tests/test_data_structures.py
tests/test_dbt_utils.py
tests/test_docker_response_reader.py
tests/test_filesystem_utils.py
tests/test_io_utils.py
tests/test_looker_utils.py
tests/test_vcs_utils.py
tests/cli_commands/__init__.py
