Metadata-Version: 2.4
Name: data_pipelines_cli
Version: 0.31.0
Summary: CLI for data platform
Home-page: https://github.com/getindata/data-pipelines-cli/
Author: Andrzej Swatowski
Author-email: andrzej.swatowski@getindata.com
License: Apache Software License (Apache 2.0)
Keywords: dbt airflow cli
Classifier: Development Status :: 1 - Planning
Classifier: Programming Language :: Python :: 3.9
Classifier: Programming Language :: Python :: 3.10
Classifier: Programming Language :: Python :: 3.11
Classifier: Programming Language :: Python :: 3.12
Requires-Python: >=3.9
License-File: LICENSE
Requires-Dist: MarkupSafe==2.1.1
Requires-Dist: Werkzeug==2.2.3
Requires-Dist: click==8.1.3
Requires-Dist: pyyaml==6.0.1
Requires-Dist: types-PyYAML==6.0.12.2
Requires-Dist: copier==7.0.1
Requires-Dist: pyyaml-include<2
Requires-Dist: pydantic<2
Requires-Dist: Jinja2==3.1.2
Requires-Dist: fsspec<2025.0.0,>=2024.6.0
Requires-Dist: packaging>=23.0
Requires-Dist: colorama==0.4.5
Requires-Dist: dbt-core==1.7.3
Provides-Extra: bigquery
Requires-Dist: dbt-bigquery==1.7.2; extra == "bigquery"
Provides-Extra: postgres
Requires-Dist: dbt-postgres==1.7.3; extra == "postgres"
Provides-Extra: snowflake
Requires-Dist: dbt-snowflake==1.7.1; extra == "snowflake"
Provides-Extra: redshift
Requires-Dist: dbt-redshift==1.7.1; extra == "redshift"
Provides-Extra: glue
Requires-Dist: dbt-glue==1.7.0; extra == "glue"
Requires-Dist: dbt-spark[session]==1.7.1; extra == "glue"
Provides-Extra: databricks
Requires-Dist: dbt-databricks-factory>=0.1.1; extra == "databricks"
Provides-Extra: dbt-all
Requires-Dist: dbt-bigquery==1.7.2; extra == "dbt-all"
Requires-Dist: dbt-postgres==1.7.3; extra == "dbt-all"
Requires-Dist: dbt-snowflake==1.7.1; extra == "dbt-all"
Requires-Dist: dbt-redshift==1.7.1; extra == "dbt-all"
Requires-Dist: dbt-glue==1.7.0; extra == "dbt-all"
Provides-Extra: docker
Requires-Dist: docker==6.0.1; extra == "docker"
Provides-Extra: datahub
Requires-Dist: acryl-datahub[dbt]==0.12.0.5; extra == "datahub"
Provides-Extra: git
Requires-Dist: GitPython==3.1.29; extra == "git"
Provides-Extra: looker
Requires-Dist: dbt2looker==0.11.0; extra == "looker"
Provides-Extra: tests
Requires-Dist: pytest==7.2.0; extra == "tests"
Requires-Dist: pytest-cov==4.0.0; extra == "tests"
Requires-Dist: pre-commit==2.20.0; extra == "tests"
Requires-Dist: tox==3.27.1; extra == "tests"
Requires-Dist: tox-gh-actions==2.12.0; extra == "tests"
Requires-Dist: moto[s3,server]<5.0.0,>=4.2.0; extra == "tests"
Requires-Dist: gcp-storage-emulator==2022.6.11; extra == "tests"
Requires-Dist: GitPython==3.1.29; extra == "tests"
Requires-Dist: types-requests==2.28.11.5; extra == "tests"
Requires-Dist: gcsfs<2025.0.0,>=2024.6.0; extra == "tests"
Requires-Dist: s3fs<2025.0.0,>=2024.6.0; extra == "tests"
Provides-Extra: docs
Requires-Dist: sphinx==5.3.0; extra == "docs"
Requires-Dist: sphinx-rtd-theme==1.1.1; extra == "docs"
Requires-Dist: sphinx-click==4.4.0; extra == "docs"
Requires-Dist: myst-parser==0.18.1; extra == "docs"
Requires-Dist: GitPython==3.1.29; extra == "docs"
Requires-Dist: colorama==0.4.5; extra == "docs"
Requires-Dist: pytz==2023.3; extra == "docs"
Provides-Extra: gcs
Requires-Dist: gcsfs<2025.0.0,>=2024.6.0; extra == "gcs"
Provides-Extra: s3
Requires-Dist: s3fs<2025.0.0,>=2024.6.0; extra == "s3"
Dynamic: author
Dynamic: author-email
Dynamic: classifier
Dynamic: description
Dynamic: description-content-type
Dynamic: home-page
Dynamic: keywords
Dynamic: license
Dynamic: license-file
Dynamic: provides-extra
Dynamic: requires-dist
Dynamic: requires-python
Dynamic: summary
